Metadata-Version: 2.1
Name: pg-streamline
Version: 1.2.0
Summary: pg-streamline is a Python library designed to simplify and streamline the process of logical replication
Home-page: https://github.com/shwetabhk/pg-streamline-py
Author: Shwetabh Kumar
Author-email: shwetabh002@gmail.com
License: MIT
Keywords: netsuite,api,python,sdk
Classifier: Topic :: Internet :: WWW/HTTP
Classifier: Intended Audience :: Developers
Classifier: Programming Language :: Python :: 3
Classifier: License :: OSI Approved :: MIT License
Classifier: Operating System :: OS Independent
License-File: LICENSE
Requires-Dist: pika >=1.3.2
Requires-Dist: psycopg2-binary >=2.9.9
Requires-Dist: pyyaml >=6.0.1
